nlhappy/__init__.py
nlhappy/__main__.py
nlhappy/algorithms/__init__.py
nlhappy/algorithms/text_match.py
nlhappy/callbacks/__init__.py
nlhappy/callbacks/ckpt_callbacks.py
nlhappy/configs/__init__.py
nlhappy/configs/callbacks/default.yaml
nlhappy/configs/callbacks/finetune.yaml
nlhappy/configs/callbacks/none.yaml
nlhappy/configs/callbacks/swa.yaml
nlhappy/configs/callbacks/update.yaml
nlhappy/configs/config.yaml
nlhappy/configs/datamodule/entity_extraction.yaml
nlhappy/configs/datamodule/event_extraction.yaml
nlhappy/configs/datamodule/prompt_relation_extraction.yaml
nlhappy/configs/datamodule/prompt_span_extraction.yaml
nlhappy/configs/datamodule/question_answering.yaml
nlhappy/configs/datamodule/relation_extraction.yaml
nlhappy/configs/datamodule/span_extraction.yaml
nlhappy/configs/datamodule/text_classification.yaml
nlhappy/configs/datamodule/text_pair_classification.yaml
nlhappy/configs/datamodule/text_pair_regression.yaml
nlhappy/configs/datamodule/token_classification.yaml
nlhappy/configs/log_dir/debug.yaml
nlhappy/configs/log_dir/default.yaml
nlhappy/configs/log_dir/evaluation.yaml
nlhappy/configs/logger/csv.yaml
nlhappy/configs/logger/many_loggers.yaml
nlhappy/configs/logger/tensorboard.yaml
nlhappy/configs/logger/wandb.yaml
nlhappy/configs/model/bert4qa.yaml
nlhappy/configs/model/bert4tc.yaml
nlhappy/configs/model/bert4tpc.yaml
nlhappy/configs/model/bert_bi_encoder.yaml
nlhappy/configs/model/bert_crf.yaml
nlhappy/configs/model/bert_global_span.yaml
nlhappy/configs/model/bert_lstm_crf.yaml
nlhappy/configs/model/bert_text_multi_classification.yaml
nlhappy/configs/model/bert_token_classification.yaml
nlhappy/configs/model/biaffine4ee.yaml
nlhappy/configs/model/biaffine4ner.yaml
nlhappy/configs/model/blinker4re.yaml
nlhappy/configs/model/casrel.yaml
nlhappy/configs/model/cosent.yaml
nlhappy/configs/model/crf4ner.yaml
nlhappy/configs/model/globalpointer4clique.yaml
nlhappy/configs/model/globalpointer4ner.yaml
nlhappy/configs/model/globalpointer4qa.yaml
nlhappy-2024.5.7.post1.dist-info/LICENSE
nlhappy-2024.5.7.post1.dist-info/METADATA
nlhappy-2024.5.7.post1.dist-info/WHEEL
nlhappy-2024.5.7.post1.dist-info/entry_points.txt
nlhappy-2024.5.7.post1.dist-info/RECORD
