Metadata-Version: 2.1
Name: nlhappy
Version: 2024.5.7.post1
Summary: 自然语言处理(NLP)
License: MIT
Author: wangmengdi
Author-email: 790990241@qq.om
Requires-Python: >=3.7
Classifier: License :: OSI Approved :: MIT License
Classifier: Programming Language :: Python :: 3
Classifier: Programming Language :: Python :: 3.7
Classifier: Programming Language :: Python :: 3.8
Classifier: Programming Language :: Python :: 3.9
Classifier: Programming Language :: Python :: 3.10
Classifier: Programming Language :: Python :: 3.11
Classifier: Programming Language :: Python :: 3.12
Requires-Dist: datasets (>=2.0.0)
Requires-Dist: hydra-colorlog (>=1.1.0)
Requires-Dist: hydra-core (==1.3.2)
Requires-Dist: lightning (>=2.0.0)
Requires-Dist: pydantic (>=1.10.2)
Requires-Dist: rich (>=12.4.3,<13.0.0)
Requires-Dist: srsly (>=2.4.5)
Requires-Dist: torch (>=2.0.0)
Requires-Dist: transformers (>=4.17.0)
Project-URL: Documentation, https://wangmengdi.notion.site/NLHAPPY-264f05d1084848efa42068c83539904a
